AlGUILoop/AlGUILoop.py
AlGUILoop/__init__.py
alguiloop-1.0.5.dist-info/LICENSE
alguiloop-1.0.5.dist-info/METADATA
alguiloop-1.0.5.dist-info/WHEEL
alguiloop-1.0.5.dist-info/top_level.txt
alguiloop-1.0.5.dist-info/RECORD
