Metadata-Version: 2.1
Name: alguiloop
Version: 1.0.5
Summary: A python package which allows to use while and for loops without obstructing the GUI. This is currently for tkinter, PyQt5, PyQt6, wxPython, PyForms-GUI and PySide2.
Home-page: https://github.com/alankarartist/alguiloop
Author: Alankar Singh
Author-email: alankarartist@gmail.com
License: MIT
Platform: UNKNOWN
Classifier: License :: OSI Approved :: MIT License
Classifier: Programming Language :: Python :: 3.6
Classifier: Programming Language :: Python :: 3.7
Classifier: Programming Language :: Python :: 3.8
Classifier: Programming Language :: Python :: 3.9
Requires-Dist: PyQt5
Requires-Dist: PyQt6
Requires-Dist: wxPython
Requires-Dist: PySide2
